nerdicons/.temp_icons_map.json
nerdicons/__init__.py
nerdicons/cod.py
nerdicons/custom.py
nerdicons/dev.py
nerdicons/extra.py
nerdicons/fa.py
nerdicons/fae.py
nerdicons/iec.py
nerdicons/indent.py
nerdicons/indentation.py
nerdicons/linux.py
nerdicons/md.py
nerdicons/me.py
nerdicons/nerdicons_gen.py
nerdicons/oct.py
nerdicons/pl.py
nerdicons/ple.py
nerdicons/pom.py
nerdicons/seti.py
nerdicons/weather.py
nerdicons-0.1.1.dist-info/METADATA
nerdicons-0.1.1.dist-info/WHEEL
nerdicons-0.1.1.dist-info/entry_points.txt
nerdicons-0.1.1.dist-info/RECORD
