Metadata-Version: 2.4
Name: nerdicons
Version: 0.1.1
Summary: Nerd Icons In Python
Author-email: Obito <obitodih@email.com>
Requires-Python: >=3.7
Requires-Dist: requests
